keyset_pagination/Paginator.py
keyset_pagination/__init__.py
keyset_pagination/mixins.py
django_keyset_pagination-0.97.dist-info/LICENSE
django_keyset_pagination-0.97.dist-info/METADATA
django_keyset_pagination-0.97.dist-info/WHEEL
django_keyset_pagination-0.97.dist-info/top_level.txt
django_keyset_pagination-0.97.dist-info/RECORD
